LICENSE.txt
MANIFEST.in
README.rst
requirements.txt
setup.py
pySPT/__init__.py
pySPT.egg-info/PKG-INFO
pySPT.egg-info/SOURCES.txt
pySPT.egg-info/dependency_links.txt
pySPT.egg-info/not-zip-safe
pySPT.egg-info/requirements.txt
pySPT.egg-info/requires.txt
pySPT.egg-info/top_level.txt
pySPT/catalog/__init__.py
pySPT/catalog/documentation.py
pySPT/catalog/gnfw.py
pySPT/catalog/hern.py
pySPT/catalog/nie.py
pySPT/catalog/nis.py
pySPT/catalog/shear.py
pySPT/catalog/sple.py
pySPT/decorators/__init__.py
pySPT/decorators/others.py
pySPT/decorators/profile.py
pySPT/grid/__init__.py
pySPT/grid/grid.py
pySPT/integrals/__init__.py
pySPT/integrals/conformalmapping.py
pySPT/integrals/green.py
pySPT/lensing/__init__.py
pySPT/lensing/examples.py
pySPT/lensing/lensing.py
pySPT/multiproc/__init__.py
pySPT/multiproc/multiproc.py
pySPT/sourcemapping/__init__.py
pySPT/sourcemapping/sm.py
pySPT/sources_C/HOW_TO_USE.txt
pySPT/sources_C/compile_shared_libraries.sh
pySPT/sources_C/linux/IntegrandAlphaTilde_HERNG_IS1.so
pySPT/sources_C/linux/IntegrandAlphaTilde_NIEG_IS1.so
pySPT/sources_C/linux/IntegrandAlphaTilde_NISG_IS1.so
pySPT/sources_C/linux/IntegrandPsiTilde_HERNG_IS1.so
pySPT/sources_C/linux/IntegrandPsiTilde_NIEG_IS1.so
pySPT/sources_C/linux/IntegrandPsiTilde_NISG_IS1.so
pySPT/sources_C/osx/IntegrandAlphaTilde_HERNG_IS1.so
pySPT/sources_C/osx/IntegrandAlphaTilde_HERNgNFWG_IS1.so
pySPT/sources_C/osx/IntegrandAlphaTilde_NFWG_IS1.so
pySPT/sources_C/osx/IntegrandAlphaTilde_NIEG_IS1.so
pySPT/sources_C/osx/IntegrandAlphaTilde_NISG_IS1.so
pySPT/sources_C/osx/IntegrandPsiTilde_HERNG_IS1.so
pySPT/sources_C/osx/IntegrandPsiTilde_HERNgNFWG_IS1.so
pySPT/sources_C/osx/IntegrandPsiTilde_NFWG_IS1.so
pySPT/sources_C/osx/IntegrandPsiTilde_NIEG_IS1.so
pySPT/sources_C/osx/IntegrandPsiTilde_NISG_IS1.so
pySPT/sources_C/sources/HERNG.c
pySPT/sources_C/sources/HERNgNFWG.c
pySPT/sources_C/sources/IntegrandAlphaTilde.c
pySPT/sources_C/sources/IntegrandAlphaTilde_HERNG_IS1.c
pySPT/sources_C/sources/IntegrandAlphaTilde_HERNgNFWG_IS1.c
pySPT/sources_C/sources/IntegrandAlphaTilde_NFWG_IS1.c
pySPT/sources_C/sources/IntegrandAlphaTilde_NIEG_IS1.c
pySPT/sources_C/sources/IntegrandAlphaTilde_NISG_IS1.c
