Metadata-Version: 1.1
Name: pySPT
Version: 0.1.1
Summary: Package dedicated to the source position transformation in lens modeling.
Home-page: https://github.com/owertz/pySPT
Author: Olivier Wertz
Author-email: owertz@alumni.ulg.ac.be
License: MIT
Download-URL: https://github.com/owertz/pySPT/archive/0.1.1.tar.gz
Keywords: SPT
Platform: UNKNOWN
Classifier: Development Status :: 2 - Pre-Alpha
Classifier: Intended Audience :: Science/Research
Classifier: License :: OSI Approved :: MIT License
Classifier: Operating System :: MacOS :: MacOS X
Classifier: Operating System :: POSIX :: Linux
Classifier: Natural Language :: English
Classifier: Programming Language :: Python :: 2.7
